{   
    "border": "rounded-box border-none dark:border-gray-50 border-gray-50 border-solid",
    "space": "p-8",
    "color": "bg-gray-50 dark:bg-gray-900 dark:text-gray-200",
    "image": "transition-opacity ease-in duration-1000 opacity-0 w-64 h-64 xs:w-full xs:h-full md:w-64 md:h-64 rounded-lg",
    "size": "min-h-full",
    "label": "text-xs dark:text-gray-300 text-gray-600 p-1",
    "icon": {
        "size": "h-full w-full",
        "width": "0.1",
        "color": "text-gray-400"
    }
}